archi/TP3/datapath.vhd
-- Chemin de donnees sequentiel
-- TP AS2, L3 informatique, UBO
-- S. Rubini
-- 09/01/19	SR	portage pour ghdl

library ieee;
use ieee.std_logic_1164.all;
use ieee.numeric_std.all;

entity datapath is
port(
	Clk : in std_logic;

	PC     : out std_logic_vector(31 downto 0);
	Src_PC : in std_logic;

	Bus_donnees_in  : in std_logic_vector(31 downto 0);
	Bus_donnees_out : out std_logic_vector(31 downto 0);
	Bus_adresses    : out std_logic_vector(31 downto 0);
	
	Src1, Src2, Dest : in std_logic_vector(3 downto 0);
	Banc_ecr : in std_logic; 

	Cmd_UAL : in std_logic_vector(1 downto 0);
	Imm     : in std_logic_vector(15 downto 0);
	Z,N	: out std_logic;
	
	Src_op_B, Src_adr_branch : in std_logic; 
	Banc_src : in std_logic_vector(1 downto 0)
);
end datapath;

architecture behavior of datapath is
	-- registres
	type registres is array (0 to 15) of std_logic_vector(31 downto 0);
	signal banc : registres;

	signal s_pc_int, e_pc : std_logic_vector(31 downto 0) 
					:= "00000000000000000000000000000000";
	signal s_banc_A, s_banc_B, e_banc : std_logic_vector(31 downto 0);

	-- calcul d'adresses
	signal adr_bra      : std_logic_vector(31 downto 0);
	signal pc_suivant   : std_logic_vector(31 downto 0);
	
	-- ual
	signal ual_A, ual_B : std_logic_vector(31 downto 0);
	signal s_ual        : std_logic_vector(31 downto 0);	

begin
	-- registre PC
	PC <= s_pc_int;
	process(Clk)
	begin
		if Clk'event and Clk='0' then
			s_pc_int <= e_pc;
		end if; 
	end process;
	pc_suivant <= std_logic_vector( unsigned(s_pc_int) + to_unsigned(4,32) );
	adr_bra <= std_logic_vector(signed(pc_suivant) + 
			resize(signed(Imm), 32)) when Src_adr_branch='1'
		else s_ual;
	
	e_pc <= adr_bra when src_pc = '0'
		else pc_suivant;

	-- banc de registres
	process(Clk)
	begin
		if Clk'event and Clk='0' and Banc_ecr='1' then
			banc(to_integer(unsigned(Dest))) <= e_banc;
		end if; 
	end process;
	e_banc <= s_ual      when Banc_src="01" 
	     else pc_suivant when Banc_src="10"
	     else Bus_donnees_in;
	s_banc_A <= banc(to_integer(unsigned(src1))) when Src1 /= "0000" 
	       else std_logic_vector(to_signed(0,32));
	s_banc_B <= banc(to_integer(unsigned(src2))) when Src2 /= "0000" 
	       else std_logic_vector(to_signed(0,32));

	
        -- UAL
	ual_B <= s_banc_B when Src_op_B = '1'
            else std_logic_vector( resize( signed(Imm), 32) );
	ual_A <= s_banc_A;

	s_ual <= std_logic_vector(signed(ual_A)+signed(ual_B)) when Cmd_UAL="00"
	   else	 std_logic_vector(signed(ual_A)-signed(ual_B)) when Cmd_UAL="01"
	   else	 ual_A;
	Z   <= '1' when s_ual=std_logic_vector(to_signed(0, 32))
	  else '0';
	N <= s_ual(31);

	-- bus memoire
	Bus_adresses <= s_ual;
	Bus_donnees_out <= s_banc_B;


end behavior;

archi/TP3/tb_datapath.vhd
-- Banc de test du chemin de donnees
-- TP AS2, L3 informatique, UBO
-- S. Rubini
-- 

library ieee;
use ieee.std_logic_1164.all;
use ieee.numeric_std.all;


entity tb_datapath is
end tb_datapath;

architecture test of tb_datapath is

	-- declaration de l'interface du composant chemin de donnees
	component datapath
	port (	Clk : in std_logic;
		PC  : out std_logic_vector(31 downto 0);
		Src_PC : in std_logic;

		Bus_donnees_in : in std_logic_vector(31 downto 0);
		Bus_donnees_out : out std_logic_vector(31 downto 0);
		Bus_adresses : out std_logic_vector(31 downto 0);
	
		Src1, Src2, Dest : in std_logic_vector(3 downto 0);
		Banc_Ecr : in std_logic; 

		cmd_ual : in std_logic_vector(1 downto 0);
		imm     : in std_logic_vector(15 downto 0);
		Z,N	: out std_logic;
	
		Src_Op_B, Src_adr_branch : in std_logic; 	
		Banc_src : in std_logic_vector(1 downto 0));
	end component;

	signal clk    : std_logic := '0';
	signal PC     : std_logic_vector(31 downto 0);
	signal Src_PC :  std_logic;
	
	signal Src1, Src2, Dest : std_logic_vector(3 downto 0) := "0000";
	signal Banc_Ecr :  std_logic; 

	signal Cmd_ual :  std_logic_vector(1 downto 0);
	signal Imm     :  std_logic_vector(15 downto 0);
	signal Z,N     :  std_logic;
	
	signal Src_Op_B, Src_adr_branch : std_logic; 
	signal Banc_src        :  std_logic_vector(1 downto 0);

	signal Bus_Donnees_In  : std_logic_vector(31 downto 0);
	signal Bus_Donnees_Out : std_logic_vector(31 downto 0);
	signal Bus_Adresses    : std_logic_vector(31 downto 0);

begin
	-- generation du signal d'horloge 100MHz
	clk <= not(clk) after 5  ns;

	-- instanciation du chemin de données sequentiel	
	dp : datapath port map (
		Clk => Clk,
		PC => PC,
		Src_PC => Src_PC,
		Bus_Donnees_In	=> Bus_Donnees_In,
		Bus_Donnees_Out	=> Bus_Donnees_Out,
		Bus_Adresses    => Bus_Adresses,
		Src1 => Src1,
		Src2 => Src2,
		Dest => Dest,
		Banc_Src => Banc_Src,
		Banc_Ecr => Banc_Ecr,
		Z => Z,
		N => N,
		Src_Op_B => Src_Op_B,
		Cmd_UAL => Cmd_UAL,
		Src_Adr_branch => Src_Adr_Branch,
		imm => Imm);
		

	-- generation des signaux de contrôle pour chacune des instructions du programme
	program  : process
		begin	
		-- PC=0, R0=0 t=0
		-- ADDI R0, 56, R2
		Src_PC 		<= '1';
		Banc_Src 	<= "01";
		Src1 		<= "0000";
		Src2 		<= "0000";
		Dest 		<= "0010";
		Banc_Ecr	<= '1';
		Cmd_Ual         <= "00";     -- Z=0, N=0;
		Src_Op_B        <= '0';
		Src_adr_branch  <= '-';
		Bus_Donnees_in  <= "UUUUUUUUUUUUUUUUUUUUUUUUUUUUUUUU";
		imm             <= std_logic_vector(to_signed(16#56#, 16));
		wait for 10 ns;
	
		--  PC=4, R0=0, R2=56 t=10ns
		--  SUB  R0, R2, R4

		Src_PC 	<= '1';
		Banc_Src 	<= "01";
		Src1 		<= "0000";
		Src2 		<= "0010";
		Dest 		<= "0100";
		Banc_Ecr	<= '1';
		Cmd_Ual         <= "01";     -- Z=0, N=0;
		Src_Op_B        <= '1';
		Src_adr_branch  <= '-';
		Bus_Donnees_in  <= "UUUUUUUUUUUUUUUUUUUUUUUUUUUUUUUU";
		imm             <= "----------------";
		wait for 10 ns;
		
		--  PC=8, R0=0, R2=56, R4=-56 t=20ns
		--  SW R4, 100(R2)

		Src_PC 	<= '1';
		Banc_Src 	<= "--";
		Src1 		<= "0010";
		Src2 		<= "0100";
		Dest 		<= "----";
		Banc_Ecr	<= '0';
		Cmd_Ual         <= "00";     -- Z=0, N=0;
		Src_Op_B        <= '1';
		Src_adr_branch  <= '-';
		Bus_Donnees_in  <= "UUUUUUUUUUUUUUUUUUUUUUUUUUUUUUUU";
		imm             <= std_logic_vector(to_signed(16#100#, 16));
		wait for 10 ns;
		
		--  PC=12, R0=0, R2=56, R4=-56, R156=-56 t=30ns
		--  LW 104(R2), R4

		Src_PC 	<= '1';
		Banc_Src 	<= "--";
		Src1 		<= "0010";
		Src2 		<= "----";
		Dest 		<= "0100";
		Banc_Ecr	<= '0';
		Cmd_Ual         <= "00";     -- Z=0, N=0;
		Src_Op_B        <= '1';
		Src_adr_branch  <= '-';
		Bus_Donnees_in  <= "UUUUUUUUUUUUUUUUUUUUUUUUUUUUUUUU";
		imm             <= std_logic_vector(to_signed(16#104#, 16));
		wait for 10 ns;
		
		--  PC=12, R0=0, R2=56, R4=160, R156=-56 t=40ns
		--  JSR 66,R6

		Src_PC 	<= '1';
		Banc_Src 	<= "--";
		Src1 		<= "0010";
		Src2 		<= "----";
		Dest 		<= "0100";
		Banc_Ecr	<= '0';
		Cmd_Ual         <= "00";     -- Z=0, N=0;
		Src_Op_B        <= '1';
		Src_adr_branch  <= '-';
		Bus_Donnees_in  <= "UUUUUUUUUUUUUUUUUUUUUUUUUUUUUUUU";
		imm             <= std_logic_vector(to_signed(16#104#, 16));
		wait for 10 ns;
		
		--  PC=12, R0=0, R2=56, R4=160, R156=-56 t=40ns
		wait;

	end process;


end test;

archi/TP3/tb_datapath.vcd
$date
  Wed Mar  3 16:24:42 2021
$end
$version
  GHDL v0
$end
$timescale
  1 fs
$end
$scope module standard $end
$upscope $end
$scope module std_logic_1164 $end
$upscope $end
$scope module numeric_std $end
$upscope $end
$scope module tb_datapath $end
$var reg 1 ! clk $end
$var reg 32 " pc[31:0] $end
$var reg 1 # src_pc $end
$var reg 4 $ src1[3:0] $end
$var reg 4 % src2[3:0] $end
$var reg 4 & dest[3:0] $end
$var reg 1 ' banc_ecr $end
$var reg 2 ( cmd_ual[1:0] $end
$var reg 16 ) imm[15:0] $end
$var reg 1 * z $end
$var reg 1 + n $end
$var reg 1 , src_op_b $end
$var reg 1 - src_adr_branch $end
$var reg 2 . banc_src[1:0] $end
$var reg 32 / bus_donnees_in[31:0] $end
$var reg 32 0 bus_donnees_out[31:0] $end
$var reg 32 1 bus_adresses[31:0] $end
$scope module dp $end
$var reg 1 2 clk $end
$var reg 32 3 pc[31:0] $end
$var reg 1 4 src_pc $end
$var reg 32 5 bus_donnees_in[31:0] $end
$var reg 32 6 bus_donnees_out[31:0] $end
$var reg 32 7 bus_adresses[31:0] $end
$var reg 4 8 src1[3:0] $end
$var reg 4 9 src2[3:0] $end
$var reg 4 : dest[3:0] $end
$var reg 1 ; banc_ecr $end
$var reg 2 < cmd_ual[1:0] $end
$var reg 16 = imm[15:0] $end
$var reg 1 > z $end
$var reg 1 ? n $end
$var reg 1 @ src_op_b $end
$var reg 1 A src_adr_branch $end
$var reg 2 B banc_src[1:0] $end
$comment banc is not handled $end
$var reg 32 C s_pc_int[31:0] $end
$var reg 32 D e_pc[31:0] $end
$var reg 32 E s_banc_a[31:0] $end
$var reg 32 F s_banc_b[31:0] $end
$var reg 32 G e_banc[31:0] $end
$var reg 32 H adr_bra[31:0] $end
$var reg 32 I pc_suivant[31:0] $end
$var reg 32 J ual_a[31:0] $end
$var reg 32 K ual_b[31:0] $end
$var reg 32 L s_ual[31:0] $end
$upscope $end
$upscope $end
$enddefinitions $end
#0
0!
b00000000000000000000000000000000 "
1#
b0000 $
b0000 %
b0010 &
1'
b00 (
b0000000001010110 )
0*
0+
0,
--
b01 .
bUUUUUUUUUUUUUUUUUUUUUUUUUUUUUUUU /
b00000000000000000000000000000000 0
b00000000000000000000000001010110 1
02
b00000000000000000000000000000000 3
14
bUUUUUUUUUUUUUUUUUUUUUUUUUUUUUUUU 5
b00000000000000000000000000000000 6
b00000000000000000000000001010110 7
b0000 8
b0000 9
b0010 :
1;
b00 <
b0000000001010110 =
0>
0?
0@
-A
b01 B
b00000000000000000000000000000000 C
b00000000000000000000000000000100 D
b00000000000000000000000000000000 E
b00000000000000000000000000000000 F
b00000000000000000000000001010110 G
b00000000000000000000000001010110 H
b00000000000000000000000000000100 I
b00000000000000000000000000000000 J
b00000000000000000000000001010110 K
b00000000000000000000000001010110 L
#5000000
1!
12
#10000000
0!
b00000000000000000000000000000100 "
b0010 %
b0100 &
b01 (
b---------------- )
0*
1+
1,
b00000000000000000000000001010110 0
b11111111111111111111111110101010 1
02
b00000000000000000000000000000100 3
b00000000000000000000000001010110 6
b11111111111111111111111110101010 7
b0010 9
b0100 :
b01 <
b---------------- =
0>
1?
1@
b00000000000000000000000000000100 C
b00000000000000000000000000001000 D
b00000000000000000000000001010110 F
b11111111111111111111111110101010 G
b11111111111111111111111110101010 H
b00000000000000000000000000001000 I
b00000000000000000000000001010110 K
b11111111111111111111111110101010 L
#15000000
1!
12
#20000000
0!
b00000000000000000000000000001000 "
02
b00000000000000000000000000001000 3
b00000000000000000000000000001000 C
b00000000000000000000000000001100 D
b00000000000000000000000000001100 I
#25000000
1!
12
#30000000
0!
b00000000000000000000000000001100 "
02
b00000000000000000000000000001100 3
b00000000000000000000000000001100 C
b00000000000000000000000000010000 D
b00000000000000000000000000010000 I
#35000000
1!
12
#40000000
0!
b00000000000000000000000000010000 "
02
b00000000000000000000000000010000 3
b00000000000000000000000000010000 C
b00000000000000000000000000010100 D
b00000000000000000000000000010100 I
#45000000
1!
12
#50000000
0!
b00000000000000000000000000010100 "
02
b00000000000000000000000000010100 3
b00000000000000000000000000010100 C
b00000000000000000000000000011000 D
b00000000000000000000000000011000 I
#55000000
1!
12
#60000000
0!
b00000000000000000000000000011000 "
02
b00000000000000000000000000011000 3
b00000000000000000000000000011000 C
b00000000000000000000000000011100 D
b00000000000000000000000000011100 I
#65000000
1!
12
#70000000
0!
b00000000000000000000000000011100 "
02
b00000000000000000000000000011100 3
b00000000000000000000000000011100 C
b00000000000000000000000000100000 D
b00000000000000000000000000100000 I
#75000000
1!
12
#80000000
0!
b00000000000000000000000000100000 "
02
b00000000000000000000000000100000 3
b00000000000000000000000000100000 C
b00000000000000000000000000100100 D
b00000000000000000000000000100100 I
#85000000
1!
12
#90000000
0!
b00000000000000000000000000100100 "
02
b00000000000000000000000000100100 3
b00000000000000000000000000100100 C
b00000000000000000000000000101000 D
b00000000000000000000000000101000 I
#95000000
1!
12
#100000000
0!
b00000000000000000000000000101000 "
02
b00000000000000000000000000101000 3
b00000000000000000000000000101000 C
b00000000000000000000000000101100 D
b00000000000000000000000000101100 I
#105000000
1!
12
#110000000
0!
b00000000000000000000000000101100 "
02
b00000000000000000000000000101100 3
b00000000000000000000000000101100 C
b00000000000000000000000000110000 D
b00000000000000000000000000110000 I
#115000000
1!
12
#120000000
0!
b00000000000000000000000000110000 "
02
b00000000000000000000000000110000 3
b00000000000000000000000000110000 C
b00000000000000000000000000110100 D
b00000000000000000000000000110100 I
#125000000
1!
12
#130000000
0!
b00000000000000000000000000110100 "
02
b00000000000000000000000000110100 3
b00000000000000000000000000110100 C
b00000000000000000000000000111000 D
b00000000000000000000000000111000 I
#135000000
1!
12
#140000000
0!
b00000000000000000000000000111000 "
02
b00000000000000000000000000111000 3
b00000000000000000000000000111000 C
b00000000000000000000000000111100 D
b00000000000000000000000000111100 I
#145000000
1!
12
#150000000
0!
b00000000000000000000000000111100 "
02
b00000000000000000000000000111100 3
b00000000000000000000000000111100 C
b00000000000000000000000001000000 D
b00000000000000000000000001000000 I
#155000000
1!
12
#160000000
0!
b00000000000000000000000001000000 "
02
b00000000000000000000000001000000 3
b00000000000000000000000001000000 C
b00000000000000000000000001000100 D
b00000000000000000000000001000100 I
#165000000
1!
12
#170000000
0!
b00000000000000000000000001000100 "
02
b00000000000000000000000001000100 3
b00000000000000000000000001000100 C
b00000000000000000000000001001000 D
b00000000000000000000000001001000 I
#175000000
1!
12
#180000000
0!
b00000000000000000000000001001000 "
02
b00000000000000000000000001001000 3
b00000000000000000000000001001000 C
b00000000000000000000000001001100 D
b00000000000000000000000001001100 I
#185000000
1!
12
#190000000
0!
b00000000000000000000000001001100 "
02
b00000000000000000000000001001100 3
b00000000000000000000000001001100 C
b00000000000000000000000001010000 D
b00000000000000000000000001010000 I
#195000000
1!
12
#200000000
0!
b00000000000000000000000001010000 "
02
b00000000000000000000000001010000 3
b00000000000000000000000001010000 C
b00000000000000000000000001010100 D
b00000000000000000000000001010100 I
#205000000
1!
12
#210000000
0!
b00000000000000000000000001010100 "
02
b00000000000000000000000001010100 3
b00000000000000000000000001010100 C
b00000000000000000000000001011000 D
b00000000000000000000000001011000 I
#215000000
1!
12
#220000000
0!
b00000000000000000000000001011000 "
02
b00000000000000000000000001011000 3
b00000000000000000000000001011000 C
b00000000000000000000000001011100 D
b00000000000000000000000001011100 I
#225000000
1!
12
#230000000
0!
b00000000000000000000000001011100 "
02
b00000000000000000000000001011100 3
b00000000000000000000000001011100 C
b00000000000000000000000001100000 D
b00000000000000000000000001100000 I
#235000000
1!
12
#240000000
0!
b00000000000000000000000001100000 "
02
b00000000000000000000000001100000 3
b00000000000000000000000001100000 C
b00000000000000000000000001100100 D
b00000000000000000000000001100100 I
#245000000
1!
12
#250000000
0!
b00000000000000000000000001100100 "
02
b00000000000000000000000001100100 3
b00000000000000000000000001100100 C
b00000000000000000000000001101000 D
b00000000000000000000000001101000 I
#255000000
1!
12
#260000000
0!
b00000000000000000000000001101000 "
02
b00000000000000000000000001101000 3
b00000000000000000000000001101000 C
b00000000000000000000000001101100 D
b00000000000000000000000001101100 I
#265000000
1!
12
#270000000
0!
b00000000000000000000000001101100 "
02
b00000000000000000000000001101100 3
b00000000000000000000000001101100 C
b00000000000000000000000001110000 D
b00000000000000000000000001110000 I
#275000000
1!
12
#280000000
0!
b00000000000000000000000001110000 "
02
b00000000000000000000000001110000 3
b00000000000000000000000001110000 C
b00000000000000000000000001110100 D
b00000000000000000000000001110100 I
#285000000
1!
12
#290000000
0!
b00000000000000000000000001110100 "
02
b00000000000000000000000001110100 3
b00000000000000000000000001110100 C
b00000000000000000000000001111000 D
b00000000000000000000000001111000 I
#295000000
1!
12
#300000000
0!
b00000000000000000000000001111000 "
02
b00000000000000000000000001111000 3
b00000000000000000000000001111000 C
b00000000000000000000000001111100 D
b00000000000000000000000001111100 I
#305000000
1!
12
#310000000
0!
b00000000000000000000000001111100 "
02
b00000000000000000000000001111100 3
b00000000000000000000000001111100 C
b00000000000000000000000010000000 D
b00000000000000000000000010000000 I
#315000000
1!
12
#320000000
0!
b00000000000000000000000010000000 "
02
b00000000000000000000000010000000 3
b00000000000000000000000010000000 C
b00000000000000000000000010000100 D
b00000000000000000000000010000100 I
#325000000
1!
12
#330000000
0!
b00000000000000000000000010000100 "
02
b00000000000000000000000010000100 3
b00000000000000000000000010000100 C
b00000000000000000000000010001000 D
b00000000000000000000000010001000 I
#335000000
1!
12
#340000000
0!
b00000000000000000000000010001000 "
02
b00000000000000000000000010001000 3
b00000000000000000000000010001000 C
b00000000000000000000000010001100 D
b00000000000000000000000010001100 I
#345000000
1!
12
#350000000
0!
b00000000000000000000000010001100 "
02
b00000000000000000000000010001100 3
b00000000000000000000000010001100 C
b00000000000000000000000010010000 D
b00000000000000000000000010010000 I
#355000000
1!
12
#360000000
0!
b00000000000000000000000010010000 "
02
b00000000000000000000000010010000 3
b00000000000000000000000010010000 C
b00000000000000000000000010010100 D
b00000000000000000000000010010100 I
#365000000
1!
12
#370000000
0!
b00000000000000000000000010010100 "
02
b00000000000000000000000010010100 3
b00000000000000000000000010010100 C
b00000000000000000000000010011000 D
b00000000000000000000000010011000 I
#375000000
1!
12
#380000000
0!
b00000000000000000000000010011000 "
02
b00000000000000000000000010011000 3
b00000000000000000000000010011000 C
b00000000000000000000000010011100 D
b00000000000000000000000010011100 I
#385000000
1!
12
#390000000
0!
b00000000000000000000000010011100 "
02
b00000000000000000000000010011100 3
b00000000000000000000000010011100 C
b00000000000000000000000010100000 D
b00000000000000000000000010100000 I
#395000000
1!
12
#400000000
0!
b00000000000000000000000010100000 "
02
b00000000000000000000000010100000 3
b00000000000000000000000010100000 C
b00000000000000000000000010100100 D
b00000000000000000000000010100100 I
#405000000
1!
12
#410000000
0!
b00000000000000000000000010100100 "
02
b00000000000000000000000010100100 3
b00000000000000000000000010100100 C
b00000000000000000000000010101000 D
b00000000000000000000000010101000 I
#415000000
1!
12
#420000000
0!
b00000000000000000000000010101000 "
02
b00000000000000000000000010101000 3
b00000000000000000000000010101000 C
b00000000000000000000000010101100 D
b00000000000000000000000010101100 I
#425000000
1!
12
#430000000
0!
b00000000000000000000000010101100 "
02
b00000000000000000000000010101100 3
b00000000000000000000000010101100 C
b00000000000000000000000010110000 D
b00000000000000000000000010110000 I
#435000000
1!
12
#440000000
0!
b00000000000000000000000010110000 "
02
b00000000000000000000000010110000 3
b00000000000000000000000010110000 C
b00000000000000000000000010110100 D
b00000000000000000000000010110100 I
#445000000
1!
12
#450000000
0!
b00000000000000000000000010110100 "
02
b00000000000000000000000010110100 3
b00000000000000000000000010110100 C
b00000000000000000000000010111000 D
b00000000000000000000000010111000 I
#455000000
1!
12
#460000000
0!
b00000000000000000000000010111000 "
02
b00000000000000000000000010111000 3
b00000000000000000000000010111000 C
b00000000000000000000000010111100 D
b00000000000000000000000010111100 I
#465000000
1!
12
#470000000
0!
b00000000000000000000000010111100 "
02
b00000000000000000000000010111100 3
b00000000000000000000000010111100 C
b00000000000000000000000011000000 D
b00000000000000000000000011000000 I
#475000000
1!
12
#480000000
0!
b00000000000000000000000011000000 "
02
b00000000000000000000000011000000 3
b00000000000000000000000011000000 C
b00000000000000000000000011000100 D
b00000000000000000000000011000100 I
#485000000
1!
12
#490000000
0!
b00000000000000000000000011000100 "
02
b00000000000000000000000011000100 3
b00000000000000000000000011000100 C
b00000000000000000000000011001000 D
b00000000000000000000000011001000 I
#495000000
1!
12
#500000000
0!
b00000000000000000000000011001000 "
02
b00000000000000000000000011001000 3
b00000000000000000000000011001000 C
b00000000000000000000000011001100 D
b00000000000000000000000011001100 I
