archi/TP1/mux2.vhd
library ieee;
use ieee.std_logic_1164.all;

entity mux2 is
port (
	a,b,c : in std_logic;
	s	  : out std_logic
);
end mux2;
architecture beh of mux2 is
begin
	s <= a when c='0' else b;
end beh;

archi/TP1/tb_mux2.vhd
library ieee;
use ieee.std_logic_1164.all;

entity tb_mux2 is
end tb_mux2;
architecture test of tb_mux2 is
signal ta, tb, tc, ts : std_logic;
component mux2
port (
	a,b,c : in std_logic;
	s	  : out std_logic
);
end component;
begin
	iut: mux2 port map (a => ta, b => tb, c => tc, s => ts );
	ta <= '0', '0' after 10 ms, '0' after 20 ms, '0' after 30 ms, '1' after 40 ms, '1' after 50 ms, '1' after 60 ms, '0' after 70 ms;
	tb <= '0', '0' after 10 ms, '1' after 20 ms, '1' after 30 ms, '0' after 40 ms, '0' after 50 ms, '1' after 60 ms, '0' after 70 ms;
	tc <= '0', '1' after 10 ms, '0' after 20 ms, '1' after 30 ms, '0' after 40 ms, '1' after 50 ms, '1' after 60 ms, '0' after 70 ms;
end test;

archi/TP1/tb_mux2.vcd
$date
  Wed Feb 10 17:49:09 2021
$end
$version
  GHDL v0
$end
$timescale
  1 fs
$end
$scope module standard $end
$upscope $end
$scope module std_logic_1164 $end
$upscope $end
$scope module tb_mux2 $end
$var reg 1 ! ta $end
$var reg 1 " tb $end
$var reg 1 # tc $end
$var reg 1 $ ts $end
$scope module iut $end
$var reg 1 % a $end
$var reg 1 & b $end
$var reg 1 ' c $end
$var reg 1 ( s $end
$upscope $end
$upscope $end
$enddefinitions $end
#0
0!
0"
0#
0$
0%
0&
0'
0(
#10000000000000
1#
1'
#20000000000000
1"
0#
1&
0'
#30000000000000
1#
1$
1'
1(
#40000000000000
1!
0"
0#
1%
0&
0'
#50000000000000
1#
0$
1'
0(
#60000000000000
1"
1$
1&
1(
#70000000000000
0!
0"
0#
0$
0%
0&
0'
0(
